libname/__init__.py
libname/karmaMC.py
karmaMC-0.0.1.dist-info/METADATA
karmaMC-0.0.1.dist-info/WHEEL
karmaMC-0.0.1.dist-info/top_level.txt
karmaMC-0.0.1.dist-info/RECORD
