Metadata-Version: 2.1
Name: karmaMC
Version: 0.0.1
Summary: karmaMC is module that interacts with .adeth 
Author: greysonapepin
Author-email: greysonapepin@gmail.com
Keywords: python,video,minecraft
Classifier: Development Status :: 1 - Planning
Classifier: Intended Audience :: Developers
Classifier: Programming Language :: Python :: 3
Classifier: Operating System :: Unix
Classifier: Operating System :: MacOS :: MacOS X
Classifier: Operating System :: Microsoft :: Windows
Requires-Dist: time
Requires-Dist: pyautogui
Requires-Dist: colorama
Requires-Dist: keyboard
